plotgallery/__init__.py
plotgallery/api.py
plotgallery-0.2.0.dist-info/WHEEL
plotgallery-0.2.0.dist-info/METADATA
plotgallery-0.2.0.dist-info/RECORD
