Metadata-Version: 2.1
Name: plotgallery
Version: 0.2.0
Summary: 
Author: shughes
Author-email: shughes.uk@gmail.com
Requires-Python: >=3.7,<4.0
Classifier: Programming Language :: Python :: 3
Classifier: Programming Language :: Python :: 3.7
Classifier: Programming Language :: Python :: 3.8
Classifier: Programming Language :: Python :: 3.9
Requires-Dist: bokeh (==2.0.2)
Requires-Dist: requests (>=2.24.0,<3.0.0)
